eralchemy2/__init__.py
eralchemy2/cst.py
eralchemy2/helpers.py
eralchemy2/main.py
eralchemy2/models.py
eralchemy2/parser.py
eralchemy2/py.typed
eralchemy2/sqla.py
eralchemy2-1.4.1.dist-info/LICENSE.md
eralchemy2-1.4.1.dist-info/METADATA
eralchemy2-1.4.1.dist-info/WHEEL
eralchemy2-1.4.1.dist-info/entry_points.txt
eralchemy2-1.4.1.dist-info/top_level.txt
eralchemy2-1.4.1.dist-info/RECORD
