Metadata-Version: 2.1
Name: eralchemy2
Version: 1.4.1
Summary: Simple entity relation (ER) diagrams generation
Author-email: Florian Maurer <fmaurer@disroot.org>
License: Apache-2.0
Project-URL: homepage, https://github.com/maurerle/eralchemy2
Project-URL: repository, https://github.com/maurerle/eralchemy2
Keywords: sql,ORM,relational databases,ER diagram,render
Classifier: Development Status :: 5 - Production/Stable
Classifier: Intended Audience :: Developers
Classifier: Operating System :: OS Independent
Classifier: Topic :: Scientific/Engineering :: Visualization
Classifier: Topic :: Software Development :: Libraries :: Python Modules
Classifier: Topic :: Database
Requires-Python: >=3.8
License-File: LICENSE.md
Requires-Dist: sqlalchemy>=1.4
Requires-Dist: pygraphviz>=1.9
Provides-Extra: ci
Requires-Dist: flask-sqlalchemy>=2.5.1; extra == "ci"
Requires-Dist: psycopg2>=2.9.3; extra == "ci"
Requires-Dist: pytest>=7.4.3; extra == "ci"
Provides-Extra: dev
Requires-Dist: ruff>=0.4.1; extra == "dev"
Requires-Dist: mypy>=1.7.0; extra == "dev"
Requires-Dist: pre-commit>=3.0.1; extra == "dev"
